{"version": 0.6, "generator": "Overpass API 0.7.62.11 87bfad18", "osm3s": {"timestamp_osm_base": "2026-04-24T05:34:05Z", "copyright": "The data included in this document is from www.openstreetmap.org. The data is made available under ODbL."}, "elements": [{"type": "node", "id": 7208137022, "lat": 21.2835012, "lon": 84.8868164, "tags": {"addr:district": "Debagarh", "addr:full": "Near Gp Office, Palsama", "addr:postcode": "768109", "addr:state": "Odisha", "addr:subdistrict": "Kundheigola P.S.", "amenity": "hospital", "name": "Goverment hospital,Palsama", "source": "OpenGovernmentData"}}, {"type": "node", "id": 7208590916, "lat": 21.6946942, "lon": 84.6712379, "tags": {"addr:district": "Debagarh", "addr:full": "Near Gp Office, Laimura", "addr:postcode": "768108", "addr:state": "Odisha", "addr:subdistrict": "Debagarh P.S.", "amenity": "hospital", "description": "Government Hospital", "name": "Government Hospital, Laimura", "source": "OpenGovernmentData"}}, {"type": "node", "id": 7214144400, "lat": 21.5346861, "lon": 84.7296698, "tags": {"addr:district": "Debagarh", "addr:full": "Near Nh 49, Deogarh", "addr:postcode": "768108", "addr:state": "Odisha", "addr:subdistrict": "Debagarh P.S.", "amenity": "hospital", "description": "District Hospital", "name": "DH Deogarh", "source": "OpenGovernmentData"}}]}