{"version": 0.6, "generator": "Overpass API 0.7.62.11 87bfad18", "osm3s": {"timestamp_osm_base": "2026-04-18T13:09:33Z", "copyright": "The data included in this document is from www.openstreetmap.org. The data is made available under ODbL."}, "elements": [{"type": "node", "id": 2344160641, "lat": 23.6356794, "lon": 88.8473986, "tags": {"amenity": "hospital", "name": "Chuadanga General Hospital"}}, {"type": "node", "id": 2344160642, "lat": 23.6142025, "lon": 88.7627066, "tags": {"amenity": "hospital", "name": "Damurhuda Upazila Health Complex"}}, {"type": "node", "id": 2350751363, "lat": 23.4112745, "lon": 88.4911883, "tags": {"amenity": "pharmacy", "name": "Garai Traders"}}, {"type": "node", "id": 2407488007, "lat": 23.6387751, "lon": 88.835198, "tags": {"amenity": "school", "name": "Adarsha Boys High School"}}, {"type": "node", "id": 2407511239, "lat": 23.6038151, "lon": 88.7772856}, {"type": "node", "id": 2407511240, "lat": 23.6035555, "lon": 88.7779962}, {"type": "node", "id": 2407511241, "lat": 23.602966, "lon": 88.7777177}, {"type": "node", "id": 2407511242, "lat": 23.6031904, "lon": 88.7770023}, {"type": "node", "id": 2407511429, "lat": 23.5985724, "lon": 88.7824795}, {"type": "node", "id": 2407511430, "lat": 23.5978201, "lon": 88.7827772}, {"type": "node", "id": 2407511431, "lat": 23.5978245, "lon": 88.7828684}, {"type": "node", "id": 2407511432, "lat": 23.5979565, "lon": 88.7831037}, {"type": "node", "id": 2407511433, "lat": 23.5983524, "lon": 88.7836702}, {"type": "node", "id": 2407511434, "lat": 23.5990608, "lon": 88.7831037}, {"type": "node", "id": 2407516743, "lat": 23.5750446, "lon": 88.7093807, "tags": {"amenity": "place_of_worship", "building": "yes", "name": "\u0995\u09be\u09b0\u09cd\u09aa\u09be\u09b8\u09a1\u09be\u0999\u09cd\u0997\u09be \u0988\u09a6\u0997\u09be\u09b9", "name:en": "Karpashdanga Eidgah", "religion": "muslim"}}, {"type": "node", "id": 2407517213, "lat": 23.5739492, "lon": 88.7100435}, {"type": "node", "id": 2407517214, "lat": 23.5730383, "lon": 88.7096786}, {"type": "node", "id": 2407517215, "lat": 23.5733199, "lon": 88.7089056}, {"type": "node", "id": 2407517216, "lat": 23.5739492, "lon": 88.7089536}, {"type": "node", "id": 2407517217, "lat": 23.5743144, "lon": 88.7091697}, {"type": "node", "id": 2407518052, "lat": 23.6650485, "lon": 88.6036721, "tags": {"amenity": "school", "name": "Mujibnagar High School"}}, {"type": "node", "id": 2453809600, "lat": 23.3030425, "lon": 88.5309672, "tags": {"amenity": "restaurant"}}, {"type": "node", "id": 2583178144, "lat": 23.4069401, "lon": 88.4839679}, {"type": "node", "id": 2583178145, "lat": 23.4064024, "lon": 88.4841363}, {"type": "node", "id": 2583178146, "lat": 23.4061659, "lon": 88.4831078}, {"type": "node", "id": 2583178147, "lat": 23.4069105, "lon": 88.4829536}, {"type": "node", "id": 2601186315, "lat": 23.4071364, "lon": 88.4824189, "tags": {"amenity": "atm", "operator": "State Bank of India"}}, {"type": "node", "id": 3220652322, "lat": 23.6440868, "lon": 88.5949964}, {"type": "node", "id": 3220652323, "lat": 23.6440914, "lon": 88.5946286}, {"type": "node", "id": 3220652325, "lat": 23.6442044, "lon": 88.5933227}, {"type": "node", "id": 3220652327, "lat": 23.644313, "lon": 88.5925427}, {"type": "node", "id": 3220652329, "lat": 23.6444712, "lon": 88.5915972}, {"type": "node", "id": 3220652345, "lat": 23.6460677, "lon": 88.5953963}, {"type": "node", "id": 3220655164, "lat": 23.6469089, "lon": 88.5937547}, {"type": "node", "id": 3220655166, "lat": 23.6469157, "lon": 88.593614}, {"type": "node", "id": 3220655176, "lat": 23.6469541, "lon": 88.5939004}, {"type": "node", "id": 3220655183, "lat": 23.6470016, "lon": 88.5934486}, {"type": "node", "id": 3220655203, "lat": 23.6470853, "lon": 88.593972}, {"type": "node", "id": 3220655226, "lat": 23.6472323, "lon": 88.5939522}, {"type": "node", "id": 3220655239, "lat": 23.6473478, "lon": 88.5974397}, {"type": "node", "id": 3220655241, "lat": 23.6473622, "lon": 88.5973795}, {"type": "node", "id": 3220655247, "lat": 23.6474426, "lon": 88.5938214}, {"type": "node", "id": 3220655248, "lat": 23.6475421, "lon": 88.5959176}, {"type": "node", "id": 3220655249, "lat": 23.6475525, "lon": 88.5958731}, {"type": "node", "id": 3220655250, "lat": 23.6475828, "lon": 88.5939251}, {"type": "node", "id": 3220655254, "lat": 23.6478323, "lon": 88.596992}, {"type": "node", "id": 3220655256, "lat": 23.648009, "lon": 88.596862}, {"type": "node", "id": 3220655257, "lat": 23.6480146, "lon": 88.5966647}, {"type": "node", "id": 3220655259, "lat": 23.6480194, "lon": 88.5975654}, {"type": "node", "id": 3220655260, "lat": 23.6480649, "lon": 88.5966996}, {"type": "node", "id": 3220655261, "lat": 23.6480681, "lon": 88.5968637}, {"type": "node", "id": 3220655262, "lat": 23.6481137, "lon": 88.5968803}, {"type": "node", "id": 3220655263, "lat": 23.6481353, "lon": 88.5967145}, {"type": "node", "id": 3220655264, "lat": 23.6482296, "lon": 88.5960136}, {"type": "node", "id": 3220655266, "lat": 23.6482905, "lon": 88.5958678}, {"type": "node", "id": 3220655275, "lat": 23.6495636, "lon": 88.5954926}, {"type": "node", "id": 3220655276, "lat": 23.6500814, "lon": 88.5962282}, {"type": "node", "id": 3220655282, "lat": 23.6507914, "lon": 88.5963368}, {"type": "node", "id": 3220655283, "lat": 23.6508706, "lon": 88.5964504}, {"type": "node", "id": 3220662584, "lat": 23.6690303, "lon": 88.6044906}, {"type": "node", "id": 3220662585, "lat": 23.6690959, "lon": 88.6027577}, {"type": "node", "id": 3220662586, "lat": 23.6691208, "lon": 88.6028836}, {"type": "node", "id": 3220662587, "lat": 23.6691841, "lon": 88.602111}, {"type": "node", "id": 3220662588, "lat": 23.6698058, "lon": 88.6045301}, {"type": "node", "id": 3220662589, "lat": 23.6699528, "lon": 88.6021529}, {"type": "node", "id": 3374602544, "lat": 23.6424172, "lon": 88.8420829}, {"type": "node", "id": 3374602545, "lat": 23.6429819, "lon": 88.8414967}, {"type": "node", "id": 3374602546, "lat": 23.6433651, "lon": 88.8418844}, {"type": "node", "id": 3374602547, "lat": 23.6429142, "lon": 88.8424927}, {"type": "node", "id": 4023280589, "lat": 23.4086448, "lon": 88.4950266, "tags": {"amenity": "bank", "atm": "yes", "brand:wikidata": "Q2003549", "brand:wikipedia": "en:Axis Bank", "name": "Axis Bank", "name:en": "Axis Bank", "website": "https://www.axisbank.com"}}, {"type": "node", "id": 4479302090, "lat": 23.4068073, "lon": 88.8981026, "tags": {"amenity": "bank"}}, {"type": "node", "id": 4747062014, "lat": 23.64088, "lon": 88.8568208, "tags": {"amenity": "restaurant", "name": "Kalipod Mistanno Bhandar"}}, {"type": "node", "id": 4747062856, "lat": 23.621763, "lon": 88.6594995, "tags": {"addr:street": "Shibnogor Rd", "leisure": "park", "name": "DC Eco Park"}}, {"type": "node", "id": 4747062871, "lat": 23.6270161, "lon": 88.6568724}, {"type": "node", "id": 4747062872, "lat": 23.6265095, "lon": 88.6614582}, {"type": "node", "id": 4747062873, "lat": 23.6225166, "lon": 88.6611818}, {"type": "node", "id": 4747062874, "lat": 23.6198049, "lon": 88.6591165}, {"type": "node", "id": 4747062875, "lat": 23.6180169, "lon": 88.6580595}, {"type": "node", "id": 4747062876, "lat": 23.6187917, "lon": 88.6553275}, {"type": "node", "id": 4747062877, "lat": 23.6218461, "lon": 88.6537501}, {"type": "node", "id": 4747259881, "lat": 23.6527657, "lon": 88.5895748, "tags": {"amenity": "place_of_worship", "name": "Bhoberpara Church", "religion": "christian"}}, {"type": "node", "id": 5199824980, "lat": 23.3126928, "lon": 88.6404514}, {"type": "node", "id": 5199824981, "lat": 23.3126586, "lon": 88.6404503}, {"type": "node", "id": 5199824982, "lat": 23.312658, "lon": 88.6405875}, {"type": "node", "id": 5199824983, "lat": 23.3126199, "lon": 88.640616}, {"type": "node", "id": 5199824984, "lat": 23.3125288, "lon": 88.6406223}, {"type": "node", "id": 5199824985, "lat": 23.3125345, "lon": 88.6404041}, {"type": "node", "id": 5199824986, "lat": 23.3124399, "lon": 88.6404047}, {"type": "node", "id": 5199824987, "lat": 23.3124445, "lon": 88.640292}, {"type": "node", "id": 5199824988, "lat": 23.3126951, "lon": 88.6402988}, {"type": "node", "id": 5199825161, "lat": 23.3119741, "lon": 88.6402965}, {"type": "node", "id": 5199825162, "lat": 23.3119912, "lon": 88.6403899}, {"type": "node", "id": 5199825163, "lat": 23.3120082, "lon": 88.6404389}, {"type": "node", "id": 5199825164, "lat": 23.3120379, "lon": 88.6404753}, {"type": "node", "id": 5199825165, "lat": 23.3120891, "lon": 88.6405061}, {"type": "node", "id": 5199825166, "lat": 23.3124001, "lon": 88.6406439}, {"type": "node", "id": 5199825167, "lat": 23.312424, "lon": 88.6402931}, {"type": "node", "id": 5199825168, "lat": 23.3075901, "lon": 88.6427966}, {"type": "node", "id": 5199825169, "lat": 23.3075975, "lon": 88.6429959}, {"type": "node", "id": 5199825170, "lat": 23.307872, "lon": 88.6429823}, {"type": "node", "id": 5199825171, "lat": 23.3078668, "lon": 88.642804}, {"type": "node", "id": 5237839872, "lat": 23.3578953, "lon": 88.9153084}, {"type": "node", "id": 5237839873, "lat": 23.3577869, "lon": 88.9161989}, {"type": "node", "id": 5237839874, "lat": 23.3576934, "lon": 88.9161881}, {"type": "node", "id": 5237839875, "lat": 23.3574521, "lon": 88.9161559}, {"type": "node", "id": 5237839876, "lat": 23.3573142, "lon": 88.9159736}, {"type": "node", "id": 5237839877, "lat": 23.3572748, "lon": 88.9157268}, {"type": "node", "id": 5237839878, "lat": 23.3573683, "lon": 88.9153352}, {"type": "node", "id": 5237839879, "lat": 23.3574127, "lon": 88.9151743}, {"type": "node", "id": 5237839880, "lat": 23.3574471, "lon": 88.9163022}, {"type": "node", "id": 5237839881, "lat": 23.3573387, "lon": 88.9169244}, {"type": "node", "id": 5237839882, "lat": 23.3569694, "lon": 88.916844}, {"type": "node", "id": 5237839883, "lat": 23.3571122, "lon": 88.9161895}, {"type": "node", "id": 5237840565, "lat": 23.36005, "lon": 88.913855}, {"type": "node", "id": 5237840566, "lat": 23.360115, "lon": 88.914078}, {"type": "node", "id": 5237840567, "lat": 23.359959, "lon": 88.914124}, {"type": "node", "id": 5237840568, "lat": 23.3599168, "lon": 88.9138798}, {"type": "node", "id": 5237840572, "lat": 23.3575046, "lon": 88.9152255, "tags": {"amenity": "place_of_worship", "name": "High School Mosque", "religion": "muslim"}}, {"type": "node", "id": 5237840573, "lat": 23.3573032, "lon": 88.9143423, "tags": {"amenity": "place_of_worship", "religion": "hindu"}}, {"type": "node", "id": 5237840574, "lat": 23.3568053, "lon": 88.914524, "tags": {"amenity": "school", "name": "Moheshpur Lab School"}}, {"type": "node", "id": 5237840582, "lat": 23.353861, "lon": 88.9162087, "tags": {"amenity": "place_of_worship", "name": "Mohespur Central Mosque", "religion": "muslim"}}, {"type": "node", "id": 5735876795, "lat": 23.7080046, "lon": 88.6093563, "tags": {"addr:street": "Meherpur Mujibnagar Road", "amenity": "college", "name": "Mujibnagar Government Degree College", "name:bn": "\u09ae\u09c1\u099c\u09bf\u09ac\u09a8\u0997\u09b0 \u09b8\u09b0\u0995\u09be\u09b0\u09bf \u09a1\u09bf\u0997\u09cd\u09b0\u09c0 \u0995\u09b2\u09c7\u099c"}}, {"type": "node", "id": 5738399243, "lat": 23.6499089, "lon": 88.5977239, "tags": {"amenity": "place_of_worship", "name": "Mujibnagar Mosque", "religion": "muslim"}}, {"type": "node", "id": 5738457114, "lat": 23.6531497, "lon": 88.5999147, "tags": {"leisure": "park", "name": "Anannya Park", "name:bn": "\u0985\u09a8\u09a8\u09cd\u09af\u09be \u09aa\u09be\u09b0\u09cd\u0995"}}, {"type": "node", "id": 6640185642, "lat": 23.302585, "lon": 88.6751796, "tags": {"amenity": "school", "name": "Bayergangi Primary School"}}, {"type": "node", "id": 7046543623, "lat": 23.6461618, "lon": 88.8921466}, {"type": "node", "id": 7046543624, "lat": 23.6461081, "lon": 88.8921402}, {"type": "node", "id": 7046543625, "lat": 23.6461121, "lon": 88.8921002}, {"type": "node", "id": 7046543626, "lat": 23.6461658, "lon": 88.8921065}, {"type": "node", "id": 7048784891, "lat": 23.3942394, "lon": 88.5034292, "tags": {"addr:district": "Nadia", "addr:full": "Bagula Road, Nature Bhavan,Opposite Sani Mandir, Krishna Nagar", "addr:postcode": "741101", "addr:state": "West Bengal", "amenity": "clinic", "contact:phone": "3472225317", "name": "Oriental Nursing Home and polyclinic", "source": "OpenGovernmentData"}}, {"type": "node", "id": 7053628701, "lat": 23.4046024, "lon": 88.4965521, "tags": {"addr:district": "Nadia", "addr:full": "19, Anantahari Mitra Road, Krishna Nagar", "addr:postcode": "741101", "addr:state": "West Bengal", "amenity": "hospital", "name": "Santi Laparoscopy and Fertility Centre", "source": "OpenGovernmentData"}}, {"type": "node", "id": 7053810172, "lat": 23.3993815, "lon": 88.4831022, "tags": {"addr:district": "Nadia", "addr:full": "Krishnagar", "addr:postcode": "741101", "addr:state": "West Bengal", "amenity": "hospital", "name": "Mary Immaculate Hospital", "source": "OpenGovernmentData"}}, {"type": "node", "id": 7053864897, "lat": 23.4064243, "lon": 88.4930253, "tags": {"addr:district": "Nadia", "addr:full": "28, Kurchipota Lane, Krishnanagar", "addr:postcode": "741101", "addr:state": "West Bengal", "amenity": "hospital", "contact:phone": "3472252481", "name": "Anjali Aragya Niketan - Rsby", "source": "OpenGovernmentData"}}, {"type": "node", "id": 7053867995, "lat": 23.4095857, "lon": 88.4907317, "tags": {"addr:district": "Nadia", "addr:full": "18/1, R. K. Mitra Lane, Krishnanagar", "addr:postcode": "741101", "addr:state": "West Bengal", "amenity": "hospital", "name": "Krishnagar Lions Club", "source": "OpenGovernmentData"}}, {"type": "node", "id": 7058933258, "lat": 23.4080768, "lon": 88.4914632, "tags": {"addr:district": "Nadia", "addr:full": "8/1, R.K.Mitra Lane, Patra Bazar, Krishna Nagar", "addr:postcode": "741101", "addr:state": "West Bengal", "amenity": "clinic", "name": "New Mahendra Maternity and Nursing Home", "source": "OpenGovernmentData"}}, {"type": "node", "id": 7059156473, "lat": 23.4027872, "lon": 88.4912559, "tags": {"addr:district": "Nadia", "addr:full": "Infertility Centre, 104/1 D.L. Roy Road, Krishnagar", "addr:postcode": "741101", "addr:state": "West Bengal", "amenity": "clinic", "name": "Prantik Nursing Home", "source": "OpenGovernmentData"}}, {"type": "node", "id": 7065463098, "lat": 23.6381219, "lon": 88.8290673}, {"type": "node", "id": 7065463099, "lat": 23.6379514, "lon": 88.8290669}, {"type": "node", "id": 7065463100, "lat": 23.6379518, "lon": 88.8288975}, {"type": "node", "id": 7065463101, "lat": 23.6381222, "lon": 88.8288979}, {"type": "node", "id": 7065601541, "lat": 23.6387687, "lon": 88.8333448}, {"type": "node", "id": 7065601542, "lat": 23.6385611, "lon": 88.8333474}, {"type": "node", "id": 7065601543, "lat": 23.6385596, "lon": 88.8332123}, {"type": "node", "id": 7065601544, "lat": 23.6387672, "lon": 88.8332096}, {"type": "node", "id": 7068614361, "lat": 23.4074282, "lon": 88.4910724, "tags": {"addr:district": "Nadia", "addr:full": "16A, M.M. Ghosh Bye Lane, Patra Market", "addr:postcode": "741101", "addr:state": "West Bengal", "amenity": "clinic", "name": "Arogyam Nursing Home", "source": "OpenGovernmentData"}}, {"type": "node", "id": 7069112411, "lat": 23.4078092, "lon": 88.4937452, "tags": {"addr:district": "Nadia", "addr:full": "26 B L Chatterjee Road , Krishnanagar", "addr:postcode": "741101", "addr:state": "West Bengal", "amenity": "clinic", "name": "Central Nursing Home, Krishnanagar", "source": "OpenGovernmentData"}}, {"type": "node", "id": 7069112442, "lat": 23.4041132, "lon": 88.4929901, "tags": {"addr:district": "Nadia", "addr:full": "73, P.K.Bhattacharya Road, Nediarpara, Krishnagar", "addr:postcode": "741101", "addr:state": "West Bengal", "amenity": "hospital", "contact:phone": "252001", "name": "Sunview Nursing Home", "source": "OpenGovernmentData"}}, {"type": "node", "id": 7069132846, "lat": 23.6365676, "lon": 88.8444426}, {"type": "node", "id": 7069132847, "lat": 23.6367382, "lon": 88.844448}, {"type": "node", "id": 7069132848, "lat": 23.6367423, "lon": 88.8442932}, {"type": "node", "id": 7069132849, "lat": 23.6365717, "lon": 88.8442878}, {"type": "node", "id": 7071390568, "lat": 23.4062272, "lon": 88.4929522, "tags": {"addr:district": "Nadia", "addr:full": "37; Kurchipota Lane; Krishnanagar", "addr:postcode": "741101", "addr:state": "West Bengal", "amenity": "clinic", "name": "Nadia Maternity and Nursing Home", "source": "OpenGovernmentData"}}, {"type": "node", "id": 7074312583, "lat": 23.4048215, "lon": 88.4908296, "tags": {"addr:district": "Nadia", "addr:full": "9/1, Pandit L K Maitra Road,Krishnanagar", "addr:postcode": "741101", "addr:state": "West Bengal", "amenity": "hospital", "name": "Kayakalpa Sadan Nursing Home", "source": "OpenGovernmentData"}}, {"type": "node", "id": 7199716839, "lat": 23.4171884, "lon": 88.6982337, "tags": {"addr:district": "Nadia", "addr:full": "Near Khalboalia, Krishnaganj, Majdia Krishnanagar Road", "addr:postcode": "741506", "addr:state": "West Bengal", "addr:subdistrict": "Krishnaganj", "amenity": "hospital", "name": "Krishnaganj Rural Hospital", "source": "OpenGovernmentData"}}, {"type": "node", "id": 7199716873, "lat": 23.326665, "lon": 88.6428633, "tags": {"addr:district": "Nadia", "addr:full": "Nearest At Bagula Sri Krishna College, Bagula Hospital Road", "addr:postcode": "741502", "addr:state": "West Bengal", "addr:subdistrict": "Hanskhali", "amenity": "hospital", "name": "Bagula Rural Hospital", "source": "OpenGovernmentData"}}, {"type": "node", "id": 7199716988, "lat": 23.5175365, "lon": 88.5461134, "tags": {"addr:district": "Nadia", "addr:full": "East Side Of Swami Vivekananda Vidyapith, Chapra, Chapra College Road", "addr:postcode": "741123", "addr:state": "West Bengal", "addr:subdistrict": "Chapra", "amenity": "hospital", "healthcare": "centre", "name": "Chapra Rural Hospital", "source": "OpenGovernmentData"}}, {"type": "node", "id": 7199717044, "lat": 23.5197498, "lon": 88.4839096, "tags": {"addr:district": "Nadia", "addr:full": "Near Post Office, Rupdaha, Chuakhali", "addr:postcode": "741140", "addr:state": "West Bengal", "addr:subdistrict": "Krishnagar - II", "amenity": "hospital", "name": "Nawpara Rural Hospital", "source": "OpenGovernmentData"}}, {"type": "node", "id": 7668176269, "lat": 23.386676, "lon": 88.49821, "tags": {"addr:district": "Nadia", "addr:full": "Krishnanagar", "addr:postcode": "741102", "addr:state": "West Bengal", "amenity": "hospital", "name": "Shaktinagar Zilla Hospital", "source": "Local Knowledge"}}, {"type": "node", "id": 7668176279, "lat": 23.406278, "lon": 88.498423, "tags": {"addr:district": "Nadia", "addr:full": "Kanthalpota Line, Krishnanagar", "addr:postcode": "741101", "addr:state": "West Bengal", "amenity": "clinic", "name": "Shefa Eye Clinic and Nursing Home", "source": "Local Knowledge"}}, {"type": "node", "id": 7668176292, "lat": 23.391121, "lon": 88.482845, "tags": {"addr:district": "Nadia", "addr:full": "Bhatjangla, Krishnanagar", "addr:postcode": "741102", "addr:state": "West Bengal", "amenity": "hospital", "name": "Glocal Hospital", "source": "Local Knowledge"}}, {"type": "node", "id": 7668176313, "lat": 23.5214402, "lon": 88.5494408, "tags": {"addr:district": "Nadia", "addr:full": "Bangaljhi", "addr:postcode": "741123", "addr:state": "West Bengal", "amenity": "hospital", "name": "Mary Immaculate Hospital", "source": "Local Knowledge"}}, {"type": "node", "id": 7668176343, "lat": 23.3875109, "lon": 88.4979251, "tags": {"addr:district": "Nadia", "addr:full": "Krishnanagar", "addr:postcode": "741101", "addr:state": "West Bengal", "amenity": "clinic", "name": "ECHS Polyclinic", "source": "Local Knowledge"}}, {"type": "node", "id": 7668176351, "lat": 23.4051521, "lon": 88.4904756, "tags": {"addr:district": "Nadia", "addr:full": "Pandit LacK Maitra Road, Krishnanagar", "addr:postcode": "741101", "addr:state": "West Bengal", "amenity": "hospital", "name": "Bandhan Hospital", "source": "Local Knowledge"}}, {"type": "node", "id": 8687393519, "lat": 23.4233362, "lon": 88.8260318, "tags": {"amenity": "place_of_worship", "name": "\u09ac\u09be\u0987\u09a4\u09c1\u09b2 \u0986\u09ae\u09be\u09a8 \u099c\u09be\u09ae\u09c7 \u09ae\u09b8\u099c\u09bf\u09a6", "name:en": "Baitul Aman Jame Mosque", "religion": "muslim"}}, {"type": "node", "id": 8865390088, "lat": 23.6078894, "lon": 88.886678, "tags": {"addr:city": "Dingedah Bazar, Chuadanga", "addr:postcode": "7200", "addr:street": "\u099d\u09bf\u09a8\u09be\u0987\u09a6\u09be\u09b9-\u099a\u09c1\u09af\u09bc\u09be\u09a1\u09be\u0999\u09cd\u0997\u09be \u09b8\u09a1\u09bc\u0995", "name": "Global Computer Home", "name:bn": "\u0997\u09cd\u09b2\u09cb\u09ac\u09be\u09b2 \u0995\u09ae\u09cd\u09aa\u09bf\u0989\u099f\u09be\u09b0 \u09b9\u09cb\u09ae", "shop": "supermarket"}}, {"type": "node", "id": 9077556635, "lat": 23.6399193, "lon": 88.8529725}, {"type": "node", "id": 9077556636, "lat": 23.6399383, "lon": 88.8533413}, {"type": "node", "id": 9077556637, "lat": 23.6397928, "lon": 88.8533405}, {"type": "node", "id": 9077556638, "lat": 23.6397826, "lon": 88.8529674}, {"type": "node", "id": 9586150768, "lat": 23.3231327, "lon": 88.878569, "tags": {"amenity": "school", "name": "Govt Primary School"}}, {"type": "node", "id": 9586150769, "lat": 23.3509056, "lon": 88.898734, "tags": {"amenity": "school", "name": "High School"}}, {"type": "node", "id": 9586150773, "lat": 23.3943718, "lon": 88.8989559, "tags": {"amenity": "school", "name": "High School"}}, {"type": "node", "id": 9586150774, "lat": 23.4114151, "lon": 88.8650905, "tags": {"amenity": "school", "name": "High School"}}, {"type": "node", "id": 9586150775, "lat": 23.4096317, "lon": 88.8663915, "tags": {"amenity": "school", "name": "Primary School"}}, {"type": "node", "id": 9586150776, "lat": 23.4190331, "lon": 88.8261189, "tags": {"amenity": "school", "name": "High School"}}, {"type": "node", "id": 9586150777, "lat": 23.4178542, "lon": 88.8255579, "tags": {"amenity": "school", "name": "Primary School"}}, {"type": "node", "id": 9586150778, "lat": 23.3718901, "lon": 88.8378069, "tags": {"amenity": "school", "name": "Dakhil Madarasa"}}, {"type": "node", "id": 9586150779, "lat": 23.3668032, "lon": 88.8531009, "tags": {"amenity": "school", "name": "High School"}}, {"type": "node", "id": 9670848684, "lat": 23.4096546, "lon": 88.4864807, "tags": {"amenity": "college", "internet_access": "yes", "name": "Krishnagar Government College", "operator": "Kalyani University", "operator:type": "government"}}, {"type": "node", "id": 9776993025, "lat": 23.3586128, "lon": 88.9151232, "tags": {"amenity": "atm", "operator": "Dutch Bangla Bank Atm"}}, {"type": "node", "id": 9776993026, "lat": 23.3585912, "lon": 88.9150642, "tags": {"amenity": "atm", "operator": "Islami Bank Atm"}}, {"type": "node", "id": 9776993027, "lat": 23.3590242, "lon": 88.9148411, "tags": {"amenity": "pharmacy", "dispensing": "yes", "healthcare": "pharmacy", "name": "Akib Pharmacy"}}, {"type": "node", "id": 9776993028, "lat": 23.3590745, "lon": 88.914818, "tags": {"amenity": "pharmacy", "dispensing": "yes", "healthcare": "pharmacy", "name": "Sohan Pharmacy"}}, {"type": "node", "id": 9776993029, "lat": 23.3591436, "lon": 88.9147864, "tags": {"amenity": "pharmacy", "dispensing": "yes", "healthcare": "pharmacy", "name": "Saleha Drug House"}}, {"type": "node", "id": 9776993030, "lat": 23.3592049, "lon": 88.9147632, "tags": {"amenity": "pharmacy", "dispensing": "yes", "healthcare": "pharmacy", "name": "Adil Pharmacy"}}, {"type": "node", "id": 9776993031, "lat": 23.3589637, "lon": 88.914741, "tags": {"amenity": "pharmacy", "dispensing": "yes", "healthcare": "pharmacy", "name": "Jibon Pharmacy"}}, {"type": "node", "id": 9776993032, "lat": 23.3590313, "lon": 88.914711, "tags": {"amenity": "pharmacy", "dispensing": "yes", "healthcare": "pharmacy", "name": "Ma Pharmacy"}}, {"type": "node", "id": 9776993033, "lat": 23.3591193, "lon": 88.9146734, "tags": {"amenity": "pharmacy", "dispensing": "yes", "healthcare": "pharmacy", "name": "Jabed Phramacy"}}, {"type": "node", "id": 9776993034, "lat": 23.3592151, "lon": 88.9146255, "tags": {"amenity": "pharmacy", "dispensing": "yes", "healthcare": "pharmacy", "name": "Ismayel Pharmacy"}}, {"type": "node", "id": 9808631360, "lat": 23.3589483, "lon": 88.9148353, "tags": {"amenity": "restaurant", "name": "Bismillah Hotel"}}, {"type": "node", "id": 9808640335, "lat": 23.3566602, "lon": 88.9143689, "tags": {"amenity": "pharmacy", "name": "Lailee pharmacy"}}, {"type": "node", "id": 10234914618, "lat": 23.6417298, "lon": 88.8458961, "tags": {"addr:postcode": "7200", "addr:street": "Emergency Road", "amenity": "school", "name": "\u09ac\u09be\u0982\u09b2\u09be", "name:en": "Fulkuri Shishu Viddalaya", "opening_hours": "Su-Th 08:00-12:00", "operator": "Nasima Mariam"}}, {"type": "node", "id": 10250121409, "lat": 23.6427943, "lon": 88.8618564, "tags": {"amenity": "school", "name:en": "M. A. Bari High School"}}, {"type": "node", "id": 10250121509, "lat": 23.6313846, "lon": 88.8113555, "tags": {"addr:street": "\u099a\u09c1\u09df\u09be\u09a1\u09be\u0999\u09cd\u0997\u09be - \u09a6\u09b0\u09cd\u09b6\u09a8\u09be \u09b8\u09dc\u0995", "amenity": "school", "name:en": "Vimrulla Government Primary School"}}, {"type": "node", "id": 10250121609, "lat": 23.6297914, "lon": 88.841967, "tags": {"addr:street": "Belgachi Road", "amenity": "school", "name:en": "Bangladesh Open University"}}, {"type": "node", "id": 10312328509, "lat": 23.6602956, "lon": 88.8834215, "tags": {"amenity": "school", "name:en": "Chandpur Government Primary School"}}, {"type": "node", "id": 10661180522, "lat": 23.3303901, "lon": 88.6423088}, {"type": "node", "id": 10661180523, "lat": 23.3293574, "lon": 88.6422852}, {"type": "node", "id": 10661180524, "lat": 23.3292888, "lon": 88.6440941}, {"type": "node", "id": 10661180525, "lat": 23.3301915, "lon": 88.6441295}, {"type": "node", "id": 10672296002, "lat": 23.3373489, "lon": 88.6441747}, {"type": "node", "id": 10672296003, "lat": 23.3372497, "lon": 88.6447227}, {"type": "node", "id": 10672296004, "lat": 23.3361583, "lon": 88.6444963}, {"type": "node", "id": 10672296005, "lat": 23.3362079, "lon": 88.6442081}, {"type": "node", "id": 10672296006, "lat": 23.3372852, "lon": 88.6441618}, {"type": "node", "id": 10969322505, "lat": 23.3701338, "lon": 88.4830033, "tags": {"amenity": "restaurant", "name": "Mother's Hut"}}, {"type": "node", "id": 11281846009, "lat": 23.3352169, "lon": 88.6414265}, {"type": "node", "id": 11281846011, "lat": 23.3354229, "lon": 88.6409339}, {"type": "node", "id": 11281846012, "lat": 23.3354133, "lon": 88.6410793}, {"type": "node", "id": 11281846013, "lat": 23.3354308, "lon": 88.6412195}, {"type": "node", "id": 11288068948, "lat": 23.3354576, "lon": 88.6413064}, {"type": "node", "id": 11288068949, "lat": 23.335288, "lon": 88.6409347}, {"type": "node", "id": 11288068950, "lat": 23.3353436, "lon": 88.6408623}, {"type": "node", "id": 11288068951, "lat": 23.3351562, "lon": 88.6411569}, {"type": "node", "id": 11288068952, "lat": 23.3353085, "lon": 88.6409049}, {"type": "node", "id": 11288068953, "lat": 23.3351627, "lon": 88.6412398}, {"type": "node", "id": 11288068954, "lat": 23.3351907, "lon": 88.6410761}, {"type": "node", "id": 11379909781, "lat": 23.6157834, "lon": 88.8582788, "tags": {"addr:city": "chuadanga", "amenity": "place_of_worship", "name": "\u0997\u09be\u09a1\u09bc\u09be\u09ac\u09be\u09a1\u09bc\u09bf\u09af\u09bc\u09be \u0989\u09a4\u09cd\u09a4\u09b0\u09aa\u09be\u09a1\u09bc\u09be \u099c\u09be\u09ae\u09c7 \u09ae\u09b8\u099c\u09bf\u09a6", "religion": "muslim"}}, {"type": "node", "id": 11379915789, "lat": 23.6099587, "lon": 88.8593779, "tags": {"addr:city": "chuadanga", "addr:housenumber": "JV55+XP Shankarchandra", "addr:street": "\u0997\u09be\u09a1\u09bc\u09be\u09ac\u09be\u09a1\u09bc\u09c0\u09af\u09bc\u09be", "amenity": "place_of_worship", "name": "Garabaria Jame Mosque", "name:bn": "\u0997\u09be\u09a1\u09bc\u09be\u09ac\u09be\u09a1\u09bc\u09c0\u09af\u09bc\u09be \u099c\u09be\u09ae\u09c7 \u09ae\u09b8\u099c\u09bf\u09a6", "religion": "muslim"}}, {"type": "node", "id": 11471006714, "lat": 23.410614, "lon": 88.4989266}, {"type": "node", "id": 11471006715, "lat": 23.4099895, "lon": 88.4989599}, {"type": "node", "id": 11471006716, "lat": 23.4099757, "lon": 88.4988718}, {"type": "node", "id": 11471006717, "lat": 23.4098022, "lon": 88.4988804}, {"type": "node", "id": 11471006718, "lat": 23.4097627, "lon": 88.4991125}, {"type": "node", "id": 11471006719, "lat": 23.4097765, "lon": 88.499265}, {"type": "node", "id": 11471006720, "lat": 23.4099796, "lon": 88.4994541}, {"type": "node", "id": 11471006721, "lat": 23.410236, "lon": 88.4996389}, {"type": "node", "id": 11471006722, "lat": 23.4103405, "lon": 88.4997141}, {"type": "node", "id": 11471006723, "lat": 23.4121977, "lon": 88.498533}, {"type": "node", "id": 11471006724, "lat": 23.4122758, "lon": 88.4980951}, {"type": "node", "id": 11471006725, "lat": 23.4120718, "lon": 88.4978686}, {"type": "node", "id": 11471006726, "lat": 23.4117439, "lon": 88.4981806}, {"type": "node", "id": 11471006727, "lat": 23.4119843, "lon": 88.4985954}, {"type": "node", "id": 11752393022, "lat": 23.4336701, "lon": 88.6040524}, {"type": "node", "id": 11752393023, "lat": 23.4339395, "lon": 88.6041275}, {"type": "node", "id": 11752393024, "lat": 23.4340577, "lon": 88.6042509}, {"type": "node", "id": 11752393025, "lat": 23.4344268, "lon": 88.6042965}, {"type": "node", "id": 11752393026, "lat": 23.4345769, "lon": 88.6043555}, {"type": "node", "id": 11752393027, "lat": 23.4349116, "lon": 88.6044842}, {"type": "node", "id": 11752393028, "lat": 23.4348304, "lon": 88.6048088}, {"type": "node", "id": 11752393029, "lat": 23.4353189, "lon": 88.6051548}, {"type": "node", "id": 11752393030, "lat": 23.4347996, "lon": 88.6055812}, {"type": "node", "id": 11752393031, "lat": 23.4341463, "lon": 88.6046183}, {"type": "node", "id": 11752393032, "lat": 23.4338854, "lon": 88.6046773}, {"type": "node", "id": 11752393033, "lat": 23.4351828, "lon": 88.6049813}, {"type": "node", "id": 11752393034, "lat": 23.4345678, "lon": 88.6053419}, {"type": "node", "id": 11752393035, "lat": 23.4346739, "lon": 88.6054763}, {"type": "node", "id": 11752393036, "lat": 23.4337314, "lon": 88.6043554}, {"type": "node", "id": 12033089062, "lat": 23.6422574, "lon": 88.8482994}, {"type": "node", "id": 12033089063, "lat": 23.6420086, "lon": 88.8482953}, {"type": "node", "id": 12033089064, "lat": 23.642003, "lon": 88.8487042}, {"type": "node", "id": 12033089065, "lat": 23.6422519, "lon": 88.8487082}, {"type": "node", "id": 12189058975, "lat": 23.4069175, "lon": 88.486298}, {"type": "node", "id": 12189058976, "lat": 23.4069273, "lon": 88.485716}, {"type": "node", "id": 12189058977, "lat": 23.4070947, "lon": 88.4841174}, {"type": "node", "id": 12189058978, "lat": 23.4076166, "lon": 88.4847289}, {"type": "node", "id": 12189058979, "lat": 23.4075686, "lon": 88.4850964}, {"type": "node", "id": 12189058980, "lat": 23.406984, "lon": 88.4849529}, {"type": "node", "id": 12189058981, "lat": 23.4069273, "lon": 88.4866226}, {"type": "node", "id": 12189058982, "lat": 23.4070381, "lon": 88.4875774}, {"type": "node", "id": 12189058983, "lat": 23.4084658, "lon": 88.487674}, {"type": "node", "id": 12189058984, "lat": 23.4094922, "lon": 88.4887496}, {"type": "node", "id": 12189058985, "lat": 23.4104152, "lon": 88.4883526}, {"type": "node", "id": 12189058986, "lat": 23.4104349, "lon": 88.4879449}, {"type": "node", "id": 12189058987, "lat": 23.4099746, "lon": 88.4865716}, {"type": "node", "id": 12189058988, "lat": 23.4097786, "lon": 88.4856597}, {"type": "node", "id": 12189058989, "lat": 23.4097531, "lon": 88.4846887}, {"type": "node", "id": 12189058990, "lat": 23.409566, "lon": 88.4844553}, {"type": "node", "id": 12189058991, "lat": 23.4087094, "lon": 88.4842274}, {"type": "node", "id": 12189058992, "lat": 23.4079882, "lon": 88.4841576}, {"type": "node", "id": 12193373317, "lat": 23.4069246, "lon": 88.4860147}, {"type": "node", "id": 12193373318, "lat": 23.4086195, "lon": 88.4842187}, {"type": "node", "id": 12193373319, "lat": 23.4069244, "lon": 88.4860146}, {"type": "node", "id": 12374832894, "lat": 23.3932429, "lon": 88.4797778, "tags": {"amenity": "restaurant", "cuisine": "indian;regional", "level": "0", "name": "Sankar Hotel and Restaurant", "opening_hours": "24/7", "takeaway": "yes", "wheelchair": "yes"}}, {"type": "node", "id": 13355558001, "lat": 23.3908775, "lon": 88.4846479, "tags": {"addr:postcode": "741102", "addr:street": "NH12", "amenity": "restaurant", "name": "Hotel The Premium III Rashik Bangali (\u09b0\u09b8\u09bf\u0995 \u09ac\u09be\u0999\u09be\u09b2\u09bf)", "opening_hours": "Mo-Su 08:00-22:30", "phone": "+916294145096"}}, {"type": "node", "id": 13709364260, "lat": 23.3938919, "lon": 88.4929411, "tags": {"leisure": "park", "name": "Khounish Park"}}, {"type": "way", "id": 232400128, "nodes": [2407511239, 2407511240, 2407511241, 2407511242, 2407511239], "tags": {"amenity": "school", "name": "Damuhuda Pilot Girls high School"}}, {"type": "way", "id": 232400169, "nodes": [2407511429, 2407511430, 2407511431, 2407511432, 2407511433, 2407511434, 2407511429], "tags": {"amenity": "college", "name": "Wadud Shah Degree College"}}, {"type": "way", "id": 232400697, "nodes": [2407517213, 2407517214, 2407517215, 2407517216, 2407517217, 2407517213], "tags": {"amenity": "school", "name": "\u0995\u09be\u09b0\u09cd\u09aa\u09be\u09b8\u09a1\u09be\u0999\u09cd\u0997\u09be \u0989\u099a\u09cd\u099a \u09ac\u09bf\u09a6\u09cd\u09af\u09be\u09b2\u09af\u09bc", "name:en": "Karpashdanga High School"}}, {"type": "way", "id": 252226989, "nodes": [2583178144, 2583178145, 2583178146, 2583178147, 2583178144], "tags": {"amenity": "school", "name": "Holy Family Girls' School"}}, {"type": "way", "id": 315945268, "nodes": [3220652329, 3220652327, 3220652325, 3220652323, 3220652322, 3220652345, 3220655266, 3220655276, 3220655283, 3220655282, 3220655275, 3220655250, 3220655247, 3220655226, 3220655203, 3220655176, 3220655164, 3220655166, 3220655183, 3220652329], "tags": {"leisure": "park", "name": "Mujibnagar Ambagan"}}, {"type": "way", "id": 315945269, "nodes": [3220655249, 3220655248, 3220655257, 3220655260, 3220655263, 3220655264, 3220655249], "tags": {"leisure": "park"}}, {"type": "way", "id": 315945270, "nodes": [3220655262, 3220655259, 3220655239, 3220655241, 3220655254, 3220655256, 3220655261, 3220655262], "tags": {"leisure": "park"}}, {"type": "way", "id": 315946581, "nodes": [3220662589, 3220662588, 3220662584, 3220662586, 3220662585, 3220662587, 3220662589], "tags": {"addr:street": "Meherpur Mujibnagar Road", "amenity": "hospital", "emergency": "yes", "healthcare:speciality": "general", "name": "Mujibnagar Health Complex"}}, {"type": "way", "id": 330492864, "nodes": [3374602544, 3374602545, 3374602546, 3374602547, 3374602544], "tags": {"amenity": "hospital", "healthcare": "hospital", "name": "Puratan Hospital para"}}, {"type": "way", "id": 481807520, "nodes": [4747062871, 4747062872, 4747062873, 4747062874, 4747062875, 4747062876, 4747062877, 4747062871], "tags": {"leisure": "park", "name": "DC Eco Park"}}, {"type": "way", "id": 536866284, "nodes": [5199824988, 5199824987, 5199824986, 5199824985, 5199824984, 5199824983, 5199824982, 5199824981, 5199824980, 5199824988], "tags": {"amenity": "school", "name": "Bhayna Pashchimpara Primary School", "opening_hours": "Mo-Fr 11:00-16:00, Sa 11:00-13:40", "operator": "State Government", "wheelchair": "no"}}, {"type": "way", "id": 536866325, "nodes": [5199825167, 5199825166, 5199825165, 5199825164, 5199825163, 5199825162, 5199825161, 5199825167], "tags": {"amenity": "school", "name": "Bhayna Jashodamani High School", "opening_hours": "Mo-Fr 11:00-16:00, Sa 11:00-13:40", "operator": "State Government", "wheelchair": "no"}}, {"type": "way", "id": 536866326, "nodes": [5199825171, 5199825170, 5199825169, 5199825168, 5199825171], "tags": {"amenity": "school", "name": "Bhayna Purbapara Primary School", "opening_hours": "Mo-Fr 11:00-16:00, Sa 11:00-13:40", "operator": "State Government", "wheelchair": "no"}}, {"type": "way", "id": 541695905, "nodes": [5237839872, 5237839873, 5237839874, 5237839875, 5237839876, 5237839877, 5237839878, 5237839879, 5237839872], "tags": {"amenity": "school", "name": "Mohespur Boys School"}}, {"type": "way", "id": 541695907, "nodes": [5237839880, 5237839881, 5237839882, 5237839883, 5237839880], "tags": {"amenity": "school", "name": "Moheshpur Girl School"}}, {"type": "way", "id": 541695948, "nodes": [5237840565, 5237840566, 5237840567, 5237840568, 5237840565], "tags": {"amenity": "place_of_worship", "building": "yes", "religion": "muslim"}}, {"type": "way", "id": 754249083, "nodes": [7046543626, 7046543623, 7046543624, 7046543625, 7046543626], "tags": {"amenity": "school", "building": "yes"}}, {"type": "way", "id": 756439776, "nodes": [7065463101, 7065463098, 7065463099, 7065463100, 7065463101], "tags": {"amenity": "place_of_worship", "building": "yes", "name": "C & B Jame Masjid", "religion": "muslim"}}, {"type": "way", "id": 756457580, "nodes": [7065601544, 7065601541, 7065601542, 7065601543, 7065601544], "tags": {"amenity": "place_of_worship", "building": "yes", "name": "Kedargonj Jame Masjid", "religion": "muslim"}}, {"type": "way", "id": 756869448, "nodes": [7069132849, 7069132848, 7069132847, 7069132846, 7069132849], "tags": {"amenity": "place_of_worship", "building": "yes", "religion": "muslim"}}, {"type": "way", "id": 981341269, "nodes": [9077556635, 9077556636, 9077556637, 9077556638, 9077556635], "tags": {"amenity": "place_of_worship", "building": "yes", "denomination": "muslim", "name": "\u099c\u09be\u09a8\u09cd\u09a8\u09be\u09a4\u09c1\u09b2 \u09ae\u09be\u0993\u09af\u09bc\u09be \u09ae\u09b8\u099c\u09bf\u09a6", "religion": "muslim"}}, {"type": "way", "id": 1145636704, "nodes": [10661180522, 10661180523, 10661180524, 10661180525, 10661180522], "tags": {"addr:city": "Bagula, Nadia", "addr:postcode": "741502", "amenity": "college", "name": "Bagula Srikrishna College"}}, {"type": "way", "id": 1146878285, "nodes": [10672296002, 10672296003, 10672296004, 10672296005, 10672296006, 10672296002], "tags": {"building": "yes", "shop": "supermarket"}}, {"type": "way", "id": 1217584191, "nodes": [11281846009, 11288068953, 11288068951, 11288068954, 11288068949, 11288068952, 11288068950, 11281846011, 11281846012, 11281846013, 11288068948, 11281846009], "tags": {"addr:city": "Bagula", "addr:district": "Nadia", "addr:postcode": "741502", "addr:street": "Dhanhata road", "leisure": "park", "name": "Gosto Gopal Das Park", "opening_hours": "05:00-21:00"}}, {"type": "way", "id": 1235649780, "nodes": [11471006714, 11471006715, 11471006716, 11471006717, 11471006718, 11471006719, 11471006720, 11471006721, 11471006722, 11471006714], "tags": {"amenity": "bus_station", "bus": "yes", "name": "Krishnanagar Bus Stand", "public_transport": "station"}}, {"type": "way", "id": 1235649781, "nodes": [11471006723, 11471006724, 11471006725, 11471006726, 11471006727, 11471006723], "tags": {"amenity": "bus_station", "bus": "yes", "name": "Krishnanagar New Bus Stand", "public_transport": "station"}}, {"type": "way", "id": 1265079158, "nodes": [11752393022, 11752393023, 11752393024, 11752393025, 11752393026, 11752393027, 11752393028, 11752393033, 11752393029, 11752393030, 11752393035, 11752393034, 11752393031, 11752393032, 11752393036, 11752393022], "tags": {"amenity": "college"}}, {"type": "way", "id": 1298993350, "nodes": [12033089062, 12033089063, 12033089064, 12033089065, 12033089062], "tags": {"amenity": "place_of_worship", "building": "yes", "religion": "muslim"}}, {"type": "way", "id": 1317022461, "nodes": [12189058992, 12193373318, 12189058991, 12189058990, 12189058989, 12189058988, 12189058987, 12189058986, 12189058985, 12189058984, 12189058983, 12189058982, 12189058981, 12189058975, 12193373317, 12193373319, 12189058976, 12189058980, 12189058979, 12189058978, 12189058977, 12189058992], "tags": {"amenity": "college", "internet_access": "yes", "name": "Krishnagar Government College", "operator": "Kalyani University", "operator:type": "government"}}]}